Metadata-Version: 1.1
Name: Flask-Coffee
Version: 0.3
Summary: Fill your flask with coffee.
Home-page: http://terse-words.blogspot.com/2011/06/flask-coffee-fill-your-flask-with.html
Author: Col Wilson
Author-email: tersecol@gmail.com
License: BSD
Platform: any
Classifier: Environment :: Web Environment
Classifier: Intended Audience :: Developers
Classifier: License :: OSI Approved :: BSD License
Classifier: Operating System :: OS Independent
Classifier: Programming Language :: Python
Classifier: Topic :: Internet :: WWW/HTTP :: Dynamic Content
Classifier: Topic :: Software Development :: Libraries :: Python Modules
